Metadata-Version: 2.1
Name: midas2
Version: 1.1.3
Summary: https://midas2.readthedocs.io/en/latest/
Home-page: https://github.com/czbiohub/MIDAS2
Author: Chunyu Zhao and Boris Dimitrov
Author-email: chunyu.zhao@czbiohub.org
License: MIT
Project-URL: Bug Tracker, https://github.com/czbiohub/MIDAS2/issues
Project-URL: Documentation, https://midas2.readthedocs.io/en/latest/#
Project-URL: Source Code, https://github.com/czbiohub/MIDAS2
Keywords: strain-level,metagenomics,pangenome,MIDAS
Classifier: Development Status :: 5 - Production/Stable
Classifier: Natural Language :: English
Classifier: Operating System :: POSIX
Classifier: Operating System :: Unix
Classifier: Operating System :: POSIX :: Linux
Classifier: License :: OSI Approved :: MIT License
Classifier: Programming Language :: Python :: 3.9
License-File: LICENSE
Requires-Dist: biopython <=1.81
Requires-Dist: numpy
Requires-Dist: pysam >=0.21.0
Requires-Dist: gffutils >=0.12
Requires-Dist: pandas
